{
  "schedule_id": "a1b2c3d4-e5f6-7890-abcd-ef1234567001",
  "name": "Nightly Hourly Survey",
  "description": "Captures photos every hour during fixed nighttime window (01:00-06:00)",
  "schema_version": "2.0",
  "is_builtin": true,
  "trigger_type": "interval",
  "interval_trigger": {
    "interval_minutes": 60,
    "time_window": {
      "start_time": "01:00",
      "end_time": "06:00"
    }
  },
  "event_patterns": [
    {
      "pattern_id": "a1b2c3d4-e5f6-7890-abcd-ef1234567101",
      "name": "Hourly UV Capture",
      "tags": ["uv", "hourly", "nightly"],
      "actions": [
        {"action_type": "gpio", "action_name": "attract_on", "offset_minutes": 0},
        {"action_type": "gpio", "action_name": "flash_on", "offset_minutes": 1},
        {"action_type": "camera", "action_name": "takephoto", "offset_minutes": 2},
        {"action_type": "gpio", "action_name": "flash_off", "offset_minutes": 3},
        {"action_type": "gpio", "action_name": "attract_off", "offset_minutes": 4}
      ]
    }
  ]
}
